weatherstack/__init__.py
weatherstack/sdk.py
weatherstack/hooks/__init__.py
weatherstack/hooks/hook.py
weatherstack/models/__init__.py
weatherstack/models/autocomplete_ok_response.py
weatherstack/models/base.py
weatherstack/models/current_location_ok_response.py
weatherstack/models/forecast_data_ok_response.py
weatherstack/models/historical_data_ok_response.py
weatherstack/models/utils/cast_models.py
weatherstack/models/utils/json_map.py
weatherstack/net/__init__.py
weatherstack/net/environment/__init__.py
weatherstack/net/environment/environment.py
weatherstack/net/headers/__init__.py
weatherstack/net/headers/base_header.py
weatherstack/net/request_chain/__init__.py
weatherstack/net/request_chain/request_chain.py
weatherstack/net/request_chain/handlers/__init__.py
weatherstack/net/request_chain/handlers/base_handler.py
weatherstack/net/request_chain/handlers/hook_handler.py
weatherstack/net/request_chain/handlers/http_handler.py
weatherstack/net/request_chain/handlers/retry_handler.py
weatherstack/net/transport/__init__.py
weatherstack/net/transport/request.py
weatherstack/net/transport/request_error.py
weatherstack/net/transport/response.py
weatherstack/net/transport/serializer.py
weatherstack/net/transport/utils.py
weatherstack/services/__init__.py
weatherstack/services/autocomplete_location_lookup.py
weatherstack/services/current.py
weatherstack/services/forecast.py
weatherstack/services/historical.py
weatherstack/services/utils/base_service.py
weatherstack/services/utils/default_headers.py
weatherstack/services/utils/validator.py
weatherstack_client-1.0.0.dist-info/LICENSE
weatherstack_client-1.0.0.dist-info/METADATA
weatherstack_client-1.0.0.dist-info/WHEEL
weatherstack_client-1.0.0.dist-info/top_level.txt
weatherstack_client-1.0.0.dist-info/RECORD
