Metadata-Version: 2.1
Name: weatherstack-client
Version: 1.0.0
Summary: This is a weatherstack api cient
License: MIT
Requires-Python: >=3.7
License-File: LICENSE
Requires-Dist: requests >=2.31.0
